model_template_builder/__init__.py
model_template_builder/dockerize.py
model_template_builder-0.1.1.dist-info/METADATA
model_template_builder-0.1.1.dist-info/WHEEL
model_template_builder-0.1.1.dist-info/RECORD
