Metadata-Version: 2.3
Name: model-template-builder
Version: 0.1.1
Summary: building vllm models into a docker container.
Author: Abdallah Gomaa
Author-email: agomaa@perian.io
Requires-Python: >=3.10
Classifier: Programming Language :: Python :: 3
Classifier: Programming Language :: Python :: 3.10
Classifier: Programming Language :: Python :: 3.11
Classifier: Programming Language :: Python :: 3.12
Classifier: Programming Language :: Python :: 3.13
Requires-Dist: docker (>=7.1.0,<8.0.0)
Requires-Dist: huggingface-hub (>=0.34.3,<0.35.0)
Requires-Dist: transformers (>=4.54.0,<5.0.0)
